fastapy.py
fastapy-1.0.5.dist-info/LICENSE
fastapy-1.0.5.dist-info/METADATA
fastapy-1.0.5.dist-info/WHEEL
fastapy-1.0.5.dist-info/top_level.txt
fastapy-1.0.5.dist-info/RECORD
