Metadata-Version: 2.1
Name: fastapy
Version: 1.0.5
Summary: A lightweight Python module to read and write FASTA sequence records
Author-email: Andrzej Zielezinski <a.zielezinski@gmail.com>, Maciej Michalczyk <mccv99@gmail.com>
License: GNU GENERAL PUBLIC LICENSE
Project-URL: Documentation, https://github.com/aziele/fastapy
Project-URL: Source, https://github.com/aziele/fastapy
Keywords: FASTA,sequence,record,parser
Classifier: License :: OSI Approved :: GNU General Public License v3 or later (GPLv3+)
Classifier: Programming Language :: Python
Classifier: Programming Language :: Python :: 3
Classifier: Operating System :: OS Independent
Classifier: Topic :: Scientific/Engineering
Classifier: Topic :: Scientific/Engineering :: Bio-Informatics
Requires-Python: >=3.8
License-File: LICENSE
